Metadata-Version: 2.4
Name: pystorex
Version: 0.2.1
Summary: A Python state management library inspired by NgRx
Author-email: JonesHong <latte831104@gmail.com>
License: MIT
Project-URL: homepage, https://github.com/JonesHong/pystorex.git
Classifier: Programming Language :: Python :: 3
Classifier: License :: OSI Approved :: MIT License
Classifier: Operating System :: OS Independent
Requires-Python: >=3.9
License-File: LICENSE
Requires-Dist: reactivex>=1.6
Requires-Dist: pydantic>=2.11.4
Requires-Dist: immutables>=0.21
Provides-Extra: dev
Requires-Dist: twine; extra == "dev"
Requires-Dist: pytest; extra == "dev"
Requires-Dist: black; extra == "dev"
Dynamic: license-file
